[
  {
    "category": "ethernet",
    "question": "What is the maximum copper Ethernet cable length?",
    "answer": "100 meters",
    "options": [
      "100 meters",
      "55 meters",
      "185 meters",
      "500 meters"
    ],
    "note": "Twisted-pair Ethernet is commonly tested as 100 meters maximum."
  },
  {
    "category": "ethernet",
    "question": "What speed is 1000BASE-T?",
    "answer": "1 Gbps",
    "options": [
      "100 Mbps",
      "1 Gbps",
      "10 Gbps",
      "40 Gbps"
    ],
    "note": "1000BASE-T is Gigabit Ethernet over twisted pair."
  },
  {
    "category": "ethernet",
    "question": "Which Ethernet standard is 802.3ab?",
    "answer": "1000BASE-T",
    "options": [
      "100BASE-TX",
      "1000BASE-T",
      "10GBASE-T",
      "PoE"
    ],
    "note": "802.3ab is Gigabit Ethernet over copper."
  },
  {
    "category": "ethernet",
    "question": "Which Ethernet standard is 802.3ae?",
    "answer": "10 Gigabit Ethernet over fiber",
    "options": [
      "PoE",
      "Gigabit over copper",
      "10 Gigabit Ethernet over fiber",
      "Fast Ethernet"
    ],
    "note": "802.3ae is 10GbE over fiber."
  },
  {
    "category": "ethernet",
    "question": "Which Ethernet standard is 802.3an?",
    "answer": "10GBASE-T",
    "options": [
      "1000BASE-T",
      "10GBASE-T",
      "100BASE-FX",
      "PoE+"
    ],
    "note": "802.3an is 10GbE over twisted pair."
  },
  {
    "category": "copper",
    "question": "What connector is used for Ethernet twisted-pair cabling?",
    "answer": "RJ45",
    "options": [
      "RJ11",
      "RJ45",
      "LC",
      "F-type"
    ],
    "note": "RJ45 is the common Ethernet connector."
  },
  {
    "category": "copper",
    "question": "What connector is commonly used for analog phone lines?",
    "answer": "RJ11",
    "options": [
      "RJ11",
      "RJ45",
      "SC",
      "BNC"
    ],
    "note": "RJ11 is associated with phone lines."
  },
  {
    "category": "copper",
    "question": "Which cable can support 10GBASE-T up to 55 meters?",
    "answer": "Cat6",
    "options": [
      "Cat3",
      "Cat5",
      "Cat5e",
      "Cat6"
    ],
    "note": "Cat6 can support 10Gbps, but not always to 100 meters."
  },
  {
    "category": "copper",
    "question": "Which cable is designed for 10GBASE-T up to 100 meters?",
    "answer": "Cat6a",
    "options": [
      "Cat5",
      "Cat5e",
      "Cat6",
      "Cat6a"
    ],
    "note": "Cat6a is the safe exam answer for 10Gbps at 100 meters."
  },
  {
    "category": "copper",
    "question": "Which cable type is most associated with cable TV and cable internet?",
    "answer": "Coaxial",
    "options": [
      "UTP",
      "STP",
      "Coaxial",
      "Twinax"
    ],
    "note": "Coaxial cable is common for cable TV and cable internet."
  },
  {
    "category": "fiber",
    "question": "Which fiber type is used for longer distance runs?",
    "answer": "Single-mode fiber",
    "options": [
      "Single-mode fiber",
      "Multimode fiber",
      "Coaxial",
      "UTP"
    ],
    "note": "Single-mode fiber is used for longer distances."
  },
  {
    "category": "fiber",
    "question": "Which fiber type is often used for shorter LAN/backbone connections?",
    "answer": "Multimode fiber",
    "options": [
      "Single-mode fiber",
      "Multimode fiber",
      "Coaxial",
      "STP"
    ],
    "note": "Multimode is common for shorter distance fiber links."
  },
  {
    "category": "fiber",
    "question": "What does SX usually indicate in fiber Ethernet?",
    "answer": "Short wavelength / multimode",
    "options": [
      "Short wavelength / multimode",
      "Long wavelength / single-mode",
      "Copper only",
      "Wireless only"
    ],
    "note": "SX is associated with short-range multimode fiber."
  },
  {
    "category": "fiber",
    "question": "What does LX usually indicate in fiber Ethernet?",
    "answer": "Long wavelength / single-mode",
    "options": [
      "Short wavelength / multimode",
      "Long wavelength / single-mode",
      "Copper only",
      "Coax only"
    ],
    "note": "LX is associated with longer-range fiber and commonly single-mode."
  },
  {
    "category": "fiber",
    "question": "Which small fiber connector is common on modern transceivers?",
    "answer": "LC",
    "options": [
      "LC",
      "RJ45",
      "RJ11",
      "F-type"
    ],
    "note": "LC is a small form-factor fiber connector."
  },
  {
    "category": "fiber",
    "question": "Which fiber connector uses a push-pull square design?",
    "answer": "SC",
    "options": [
      "SC",
      "RJ45",
      "BNC",
      "F-type"
    ],
    "note": "SC is square and push-pull."
  },
  {
    "category": "fiber",
    "question": "Which fiber connector uses a twist-lock design?",
    "answer": "ST",
    "options": [
      "ST",
      "LC",
      "RJ11",
      "RJ45"
    ],
    "note": "ST uses a bayonet/twist style."
  },
  {
    "category": "poe",
    "question": "Which PoE standard provides about 15.4W from the switch?",
    "answer": "802.3af",
    "options": [
      "802.3af",
      "802.3at",
      "802.3bt Type 3",
      "802.3bt Type 4"
    ],
    "note": "802.3af is basic PoE."
  },
  {
    "category": "poe",
    "question": "Which PoE standard provides about 30W from the switch?",
    "answer": "802.3at",
    "options": [
      "802.3af",
      "802.3at",
      "802.3ab",
      "802.11ax"
    ],
    "note": "802.3at is PoE+."
  },
  {
    "category": "poe",
    "question": "Which PoE standard is commonly called PoE++?",
    "answer": "802.3bt",
    "options": [
      "802.3af",
      "802.3at",
      "802.3bt",
      "802.3ae"
    ],
    "note": "802.3bt is PoE++."
  },
  {
    "category": "wifi",
    "question": "Which Wi-Fi standard is Wi-Fi 4?",
    "answer": "802.11n",
    "options": [
      "802.11a",
      "802.11g",
      "802.11n",
      "802.11ac"
    ],
    "note": "Wi-Fi 4 is 802.11n."
  },
  {
    "category": "wifi",
    "question": "Which Wi-Fi standard is Wi-Fi 5?",
    "answer": "802.11ac",
    "options": [
      "802.11n",
      "802.11ac",
      "802.11ax",
      "802.11be"
    ],
    "note": "Wi-Fi 5 is 802.11ac."
  },
  {
    "category": "wifi",
    "question": "Which Wi-Fi standard is Wi-Fi 6?",
    "answer": "802.11ax",
    "options": [
      "802.11ac",
      "802.11ax",
      "802.11be",
      "802.11g"
    ],
    "note": "Wi-Fi 6 is 802.11ax."
  },
  {
    "category": "wifi",
    "question": "Which Wi-Fi standard is Wi-Fi 7?",
    "answer": "802.11be",
    "options": [
      "802.11n",
      "802.11ac",
      "802.11ax",
      "802.11be"
    ],
    "note": "Wi-Fi 7 is 802.11be."
  },
  {
    "category": "wifi",
    "question": "Which 2.4 GHz Wi-Fi channels are non-overlapping in the US?",
    "answer": "1, 6, and 11",
    "options": [
      "1, 6, and 11",
      "2, 7, and 12",
      "3, 8, and 13",
      "1, 5, and 9"
    ],
    "note": "The 1/6/11 rule is for 2.4 GHz Wi-Fi."
  },
  {
    "category": "wifi",
    "question": "Which Wi-Fi band has better range but more interference?",
    "answer": "2.4 GHz",
    "options": [
      "2.4 GHz",
      "5 GHz",
      "6 GHz",
      "60 GHz"
    ],
    "note": "2.4 GHz travels farther but is crowded."
  },
  {
    "category": "wifi",
    "question": "Which Wi-Fi 6 feature helps split channels among multiple clients?",
    "answer": "OFDMA",
    "options": [
      "NAT",
      "OFDMA",
      "SMTP",
      "LDAP"
    ],
    "note": "OFDMA is a Wi-Fi 6 feature."
  },
  {
    "category": "wifi",
    "question": "What does MIMO stand for?",
    "answer": "Multiple Input Multiple Output",
    "options": [
      "Multiple Input Multiple Output",
      "Managed Internet Mode Operation",
      "Media Input Media Output",
      "Multiple IP Multiple Objects"
    ],
    "note": "MIMO uses multiple antennas/streams to improve wireless performance."
  },
  {
    "category": "cellular",
    "question": "Which cellular generation is LTE associated with?",
    "answer": "4G",
    "options": [
      "2G",
      "3G",
      "4G",
      "5G"
    ],
    "note": "LTE is associated with 4G."
  },
  {
    "category": "cellular",
    "question": "Which is generally faster: HSPA+ or LTE?",
    "answer": "LTE",
    "options": [
      "HSPA+",
      "LTE",
      "EDGE",
      "GPRS"
    ],
    "note": "LTE is the better exam answer."
  },
  {
    "category": "cellular",
    "question": "What does GSM use for subscriber identity?",
    "answer": "SIM card",
    "options": [
      "SIM card",
      "RJ45",
      "MAC address only",
      "F-type connector"
    ],
    "note": "GSM networks use SIM cards."
  },
  {
    "category": "cellular",
    "question": "Which older cellular data term is associated with 2G?",
    "answer": "EDGE",
    "options": [
      "EDGE",
      "LTE",
      "5G NR",
      "802.11ax"
    ],
    "note": "EDGE is an older 2G-era data technology."
  },
  {
    "category": "cellular",
    "question": "What is 5G NR?",
    "answer": "5G New Radio",
    "options": [
      "5G New Radio",
      "5G Network Relay",
      "Fiber connector",
      "Cloud model"
    ],
    "note": "NR means New Radio."
  },
  {
    "category": "cloud",
    "question": "Which cloud model gives you virtual servers, storage, and networking?",
    "answer": "IaaS",
    "options": [
      "IaaS",
      "PaaS",
      "SaaS",
      "DaaS"
    ],
    "note": "IaaS gives you infrastructure; you manage the OS and above."
  },
  {
    "category": "cloud",
    "question": "Which cloud model lets you deploy your code while the provider manages the platform?",
    "answer": "PaaS",
    "options": [
      "IaaS",
      "PaaS",
      "SaaS",
      "VDI"
    ],
    "note": "PaaS is a managed platform for your app/code."
  },
  {
    "category": "cloud",
    "question": "Which cloud model is Microsoft 365 an example of?",
    "answer": "SaaS",
    "options": [
      "IaaS",
      "PaaS",
      "SaaS",
      "Private cloud"
    ],
    "note": "Microsoft 365 is software delivered as a service."
  },
  {
    "category": "cloud",
    "question": "Which cloud type combines on-premises resources with cloud resources?",
    "answer": "Hybrid cloud",
    "options": [
      "Public cloud",
      "Private cloud",
      "Hybrid cloud",
      "Community cloud"
    ],
    "note": "Hybrid cloud mixes on-premises and cloud resources."
  },
  {
    "category": "virtualization",
    "question": "Which hypervisor runs directly on hardware?",
    "answer": "Type 1",
    "options": [
      "Type 1",
      "Type 2",
      "Container",
      "Emulator"
    ],
    "note": "Type 1 is bare-metal."
  },
  {
    "category": "virtualization",
    "question": "Which hypervisor runs on top of a host OS?",
    "answer": "Type 2",
    "options": [
      "Type 1",
      "Type 2",
      "IaaS",
      "VLAN"
    ],
    "note": "VirtualBox and VMware Workstation are Type 2 examples."
  },
  {
    "category": "virtualization",
    "question": "What is Intel's CPU virtualization technology called?",
    "answer": "VT-x",
    "options": [
      "VT-x",
      "AMD-V",
      "Hyper-V",
      "OFDMA"
    ],
    "note": "Intel virtualization is VT-x."
  },
  {
    "category": "virtualization",
    "question": "What is AMD's CPU virtualization technology called?",
    "answer": "AMD-V",
    "options": [
      "VT-x",
      "AMD-V",
      "VLAN-V",
      "802.3at"
    ],
    "note": "AMD virtualization is AMD-V."
  },
  {
    "category": "ports",
    "question": "Which port does HTTPS use?",
    "answer": "443",
    "options": [
      "80",
      "110",
      "143",
      "443"
    ],
    "note": "HTTPS uses TCP 443."
  },
  {
    "category": "ports",
    "question": "Which port does HTTP use?",
    "answer": "80",
    "options": [
      "25",
      "53",
      "80",
      "443"
    ],
    "note": "HTTP uses TCP 80."
  },
  {
    "category": "ports",
    "question": "Which port does SSH use?",
    "answer": "22",
    "options": [
      "21",
      "22",
      "23",
      "3389"
    ],
    "note": "SSH uses TCP 22."
  },
  {
    "category": "ports",
    "question": "Which port does RDP use?",
    "answer": "3389",
    "options": [
      "389",
      "445",
      "1433",
      "3389"
    ],
    "note": "RDP commonly uses 3389."
  },
  {
    "category": "ports",
    "question": "Which port does DNS use?",
    "answer": "53",
    "options": [
      "25",
      "53",
      "67",
      "110"
    ],
    "note": "DNS uses port 53, commonly UDP and sometimes TCP."
  },
  {
    "category": "email",
    "question": "Which protocol sends mail between mail servers?",
    "answer": "SMTP",
    "options": [
      "POP3",
      "IMAP",
      "SMTP",
      "SNMP"
    ],
    "note": "SMTP is used to send email."
  },
  {
    "category": "email",
    "question": "Which protocol leaves mail on the server and synchronizes folders?",
    "answer": "IMAP",
    "options": [
      "POP3",
      "SMTP",
      "IMAP",
      "SNMP"
    ],
    "note": "IMAP synchronizes mail while keeping it on the server."
  },
  {
    "category": "dns",
    "question": "Which DNS record identifies mail servers for a domain?",
    "answer": "MX",
    "options": [
      "A",
      "AAAA",
      "MX",
      "TXT"
    ],
    "note": "MX records point to mail servers."
  },
  {
    "category": "dns",
    "question": "Which DNS record maps a hostname to an IPv4 address?",
    "answer": "A",
    "options": [
      "A",
      "AAAA",
      "MX",
      "PTR"
    ],
    "note": "A records map names to IPv4 addresses."
  },
  {
    "category": "dns",
    "question": "Which DNS record maps a hostname to an IPv6 address?",
    "answer": "AAAA",
    "options": [
      "A",
      "AAAA",
      "CNAME",
      "SRV"
    ],
    "note": "AAAA records map names to IPv6 addresses."
  },
  {
    "category": "storage",
    "question": "Which RAID level provides striping with parity?",
    "answer": "RAID 5",
    "options": [
      "RAID 0",
      "RAID 1",
      "RAID 5",
      "RAID 10"
    ],
    "note": "RAID 5 uses striping with parity."
  },
  {
    "category": "storage",
    "question": "Which RAID level is mirroring?",
    "answer": "RAID 1",
    "options": [
      "RAID 0",
      "RAID 1",
      "RAID 5",
      "RAID 10"
    ],
    "note": "RAID 1 mirrors data across disks."
  },
  {
    "category": "printers",
    "question": "What printer process uses a corona wire or transfer roller?",
    "answer": "Laser",
    "options": [
      "Inkjet",
      "Laser",
      "Thermal",
      "Impact"
    ],
    "note": "Laser printers use electrostatic charge during printing."
  },
  {
    "category": "ports",
    "question": "Which port does SMTP use?",
    "answer": "25",
    "options": [
      "25",
      "53",
      "110",
      "143"
    ],
    "note": "SMTP uses TCP 25."
  },
  {
    "category": "ports",
    "question": "Which secure email protocol uses port 993?",
    "answer": "IMAPS",
    "options": [
      "POP3",
      "IMAPS",
      "SMTP",
      "DNS"
    ],
    "note": "IMAPS uses TCP 993."
  },
  {
    "category": "ports",
    "question": "Which secure email protocol uses port 995?",
    "answer": "POP3S",
    "options": [
      "POP3S",
      "IMAPS",
      "SMTP",
      "LDAP"
    ],
    "note": "POP3S uses TCP 995."
  },
  {
    "category": "ports",
    "question": "Which port does LDAP use?",
    "answer": "389",
    "options": [
      "389",
      "636",
      "445",
      "3389"
    ],
    "note": "LDAP uses TCP/UDP 389."
  },
  {
    "category": "ports",
    "question": "Which secure LDAP port is commonly used?",
    "answer": "636",
    "options": [
      "389",
      "636",
      "443",
      "993"
    ],
    "note": "LDAPS uses TCP 636."
  },
  {
    "category": "ports",
    "question": "Which port does SMB use?",
    "answer": "445",
    "options": [
      "21",
      "22",
      "389",
      "445"
    ],
    "note": "Windows file sharing uses TCP 445."
  },
  {
    "category": "ports",
    "question": "Which port does DHCP use for server responses?",
    "answer": "68",
    "options": [
      "53",
      "67",
      "68",
      "69"
    ],
    "note": "Client receives DHCP on UDP 68."
  },
  {
    "category": "ports",
    "question": "Which port does DHCP use on the server?",
    "answer": "67",
    "options": [
      "67",
      "68",
      "69",
      "161"
    ],
    "note": "DHCP server listens on UDP 67."
  },
  {
    "category": "wifi",
    "question": "Which Wi-Fi standard operates only on 5 GHz and introduced MU-MIMO?",
    "answer": "802.11ac",
    "options": [
      "802.11n",
      "802.11ac",
      "802.11ax",
      "802.11be"
    ],
    "note": "Wi-Fi 5 introduced MU-MIMO."
  },
  {
    "category": "wifi",
    "question": "Which Wi-Fi standard first supported both 2.4 GHz and 5 GHz?",
    "answer": "802.11n",
    "options": [
      "802.11a",
      "802.11g",
      "802.11n",
      "802.11ac"
    ],
    "note": "802.11n supports both bands."
  },
  {
    "category": "wifi",
    "question": "Which Wi-Fi band generally provides the fastest speeds?",
    "answer": "6 GHz",
    "options": [
      "2.4 GHz",
      "5 GHz",
      "6 GHz",
      "900 MHz"
    ],
    "note": "6 GHz offers the most spectrum."
  },
  {
    "category": "cellular",
    "question": "What does HSPA+ stand for?",
    "answer": "Evolved High Speed Packet Access",
    "options": [
      "High Speed Packet Access",
      "Evolved High Speed Packet Access",
      "High Speed Packet Architecture",
      "Enhanced GSM"
    ],
    "note": "HSPA+ is a 3G technology."
  },
  {
    "category": "cellular",
    "question": "Which cellular technology is older than LTE?",
    "answer": "HSPA+",
    "options": [
      "5G NR",
      "LTE",
      "HSPA+",
      "VoLTE"
    ],
    "note": "HSPA+ predates LTE."
  },
  {
    "category": "cellular",
    "question": "What is VoLTE?",
    "answer": "Voice over LTE",
    "options": [
      "Voice over LTE",
      "Virtual LTE",
      "Video over LTE",
      "Voice over LAN"
    ],
    "note": "VoLTE carries voice traffic over LTE."
  },
  {
    "category": "cloud",
    "question": "Which cloud model provides a complete desktop environment?",
    "answer": "DaaS",
    "options": [
      "IaaS",
      "PaaS",
      "SaaS",
      "DaaS"
    ],
    "note": "Desktop as a Service."
  },
  {
    "category": "cloud",
    "question": "Which cloud type is owned and operated by a third-party provider?",
    "answer": "Public cloud",
    "options": [
      "Public cloud",
      "Private cloud",
      "Hybrid cloud",
      "Community cloud"
    ],
    "note": "Public cloud is provider-owned."
  },
  {
    "category": "cloud",
    "question": "Which cloud type is dedicated to one organization?",
    "answer": "Private cloud",
    "options": [
      "Public cloud",
      "Private cloud",
      "Hybrid cloud",
      "Community cloud"
    ],
    "note": "Private cloud is organization-owned."
  },
  {
    "category": "virtualization",
    "question": "Which Microsoft hypervisor is built into Windows Server?",
    "answer": "Hyper-V",
    "options": [
      "Hyper-V",
      "VMware",
      "KVM",
      "VirtualBox"
    ],
    "note": "Hyper-V is Microsoft's hypervisor."
  },
  {
    "category": "virtualization",
    "question": "What does VDI stand for?",
    "answer": "Virtual Desktop Infrastructure",
    "options": [
      "Virtual Desktop Infrastructure",
      "Virtual Device Interface",
      "Virtual Data Integration",
      "Visual Desktop Interface"
    ],
    "note": "VDI hosts desktops centrally."
  },
  {
    "category": "storage",
    "question": "Which RAID level offers no redundancy?",
    "answer": "RAID 0",
    "options": [
      "RAID 0",
      "RAID 1",
      "RAID 5",
      "RAID 10"
    ],
    "note": "RAID 0 is striping only."
  },
  {
    "category": "storage",
    "question": "Which RAID level combines mirroring and striping?",
    "answer": "RAID 10",
    "options": [
      "RAID 0",
      "RAID 1",
      "RAID 5",
      "RAID 10"
    ],
    "note": "RAID 10 = 1+0."
  },
  {
    "category": "storage",
    "question": "Which storage interface communicates directly over PCIe?",
    "answer": "NVMe",
    "options": [
      "SATA",
      "PATA",
      "NVMe",
      "eSATA"
    ],
    "note": "NVMe uses PCIe lanes."
  },
  {
    "category": "storage",
    "question": "What do the numbers in 2280 mean on an M.2 SSD?",
    "answer": "22mm wide and 80mm long",
    "options": [
      "22mm wide and 80mm long",
      "22GB and 80GB",
      "PCIe Gen 2 x8",
      "Transfer speed"
    ],
    "note": "Physical dimensions."
  },
  {
    "category": "dns",
    "question": "Which DNS record is commonly used for SPF?",
    "answer": "TXT",
    "options": [
      "A",
      "MX",
      "TXT",
      "PTR"
    ],
    "note": "SPF is stored in TXT records."
  },
  {
    "category": "dns",
    "question": "Which DNS record performs reverse lookups?",
    "answer": "PTR",
    "options": [
      "A",
      "AAAA",
      "PTR",
      "CNAME"
    ],
    "note": "PTR maps IP to hostname."
  },
  {
    "category": "dns",
    "question": "Which DNS record aliases one hostname to another?",
    "answer": "CNAME",
    "options": [
      "MX",
      "TXT",
      "PTR",
      "CNAME"
    ],
    "note": "CNAME creates aliases."
  },
  {
    "category": "printers",
    "question": "Which printer type uses liquid ink sprayed onto paper?",
    "answer": "Inkjet",
    "options": [
      "Laser",
      "Thermal",
      "Impact",
      "Inkjet"
    ],
    "note": "Inkjet sprays ink droplets."
  },
  {
    "category": "printers",
    "question": "Which printer type commonly uses toner?",
    "answer": "Laser",
    "options": [
      "Inkjet",
      "Laser",
      "Thermal",
      "Impact"
    ],
    "note": "Laser printers use toner."
  },
  {
    "category": "printers",
    "question": "Which printer type is commonly used for receipts?",
    "answer": "Thermal",
    "options": [
      "Inkjet",
      "Laser",
      "Thermal",
      "Dot Matrix"
    ],
    "note": "Thermal printers are common in retail."
  },
  {
    "category": "printers",
    "question": "What does IPP stand for?",
    "answer": "Internet Printing Protocol",
    "options": [
      "Internet Printing Protocol",
      "Internal Print Process",
      "Internet Print Path",
      "Integrated Printer Platform"
    ],
    "note": "IPP is a network printing protocol."
  },
  {
    "category": "mobile",
    "question": "What component stores cellular subscriber information?",
    "answer": "SIM card",
    "options": [
      "SD card",
      "SIM card",
      "eMMC",
      "NFC"
    ],
    "note": "SIM stores subscriber identity."
  },
  {
    "category": "mobile",
    "question": "What technology allows contactless payments?",
    "answer": "NFC",
    "options": [
      "Bluetooth",
      "Wi-Fi",
      "NFC",
      "GPS"
    ],
    "note": "NFC is Near Field Communication."
  },
  {
    "category": "mobile",
    "question": "What does GPS provide?",
    "answer": "Location services",
    "options": [
      "Internet access",
      "Location services",
      "Cellular calling",
      "Authentication"
    ],
    "note": "GPS provides geolocation."
  },
  {
    "category": "wifi",
    "question": "Which Wi-Fi standard introduced OFDMA?",
    "answer": "802.11ax",
    "options": [
      "802.11ac",
      "802.11ax",
      "802.11n",
      "802.11be"
    ],
    "note": "Wi-Fi 6 introduced OFDMA."
  },
  {
    "category": "wifi",
    "question": "Which Wi-Fi standard introduced MU-MIMO?",
    "answer": "802.11ac",
    "options": [
      "802.11n",
      "802.11ac",
      "802.11ax",
      "802.11be"
    ],
    "note": "MU-MIMO first appeared in Wi-Fi 5."
  },
  {
    "category": "wifi",
    "question": "What does OFDMA stand for?",
    "answer": "Orthogonal Frequency Division Multiple Access",
    "options": [
      "Orthogonal Frequency Division Multiple Access",
      "Optical Fiber Distribution Multi Access",
      "Open Frequency Dynamic Media Access",
      "Orthogonal Fiber Division Access"
    ],
    "note": "A key Wi-Fi 6 technology."
  },
  {
    "category": "cellular",
    "question": "Which cellular technology is associated with 3G networks?",
    "answer": "HSPA+",
    "options": [
      "EDGE",
      "HSPA+",
      "LTE",
      "5G NR"
    ],
    "note": "HSPA+ is commonly tested as 3G."
  },
  {
    "category": "cellular",
    "question": "Which cellular technology is associated with 5G?",
    "answer": "NR",
    "options": [
      "EDGE",
      "LTE",
      "NR",
      "GPRS"
    ],
    "note": "NR stands for New Radio."
  },
  {
    "category": "cellular",
    "question": "Which technology replaced many CDMA and GSM deployments?",
    "answer": "LTE",
    "options": [
      "EDGE",
      "HSPA+",
      "LTE",
      "GPRS"
    ],
    "note": "LTE became the dominant 4G standard."
  },
  {
    "category": "cloud",
    "question": "Who manages the operating system in SaaS?",
    "answer": "Cloud provider",
    "options": [
      "Customer",
      "Cloud provider",
      "Both",
      "Nobody"
    ],
    "note": "The provider manages everything in SaaS."
  },
  {
    "category": "cloud",
    "question": "Who manages applications in IaaS?",
    "answer": "Customer",
    "options": [
      "Customer",
      "Provider",
      "Both",
      "Neither"
    ],
    "note": "You manage OS and applications in IaaS."
  },
  {
    "category": "cloud",
    "question": "Which cloud model gives developers a platform but not server management?",
    "answer": "PaaS",
    "options": [
      "IaaS",
      "PaaS",
      "SaaS",
      "DaaS"
    ],
    "note": "PaaS abstracts infrastructure."
  },
  {
    "category": "storage",
    "question": "Which RAID level requires a minimum of 3 drives?",
    "answer": "RAID 5",
    "options": [
      "RAID 0",
      "RAID 1",
      "RAID 5",
      "RAID 10"
    ],
    "note": "RAID 5 needs at least three disks."
  },
  {
    "category": "storage",
    "question": "Which RAID level provides the fastest performance but no fault tolerance?",
    "answer": "RAID 0",
    "options": [
      "RAID 0",
      "RAID 1",
      "RAID 5",
      "RAID 10"
    ],
    "note": "RAID 0 stripes data without redundancy."
  },
  {
    "category": "storage",
    "question": "What does S.M.A.R.T. monitor?",
    "answer": "Drive health",
    "options": [
      "Network performance",
      "Drive health",
      "CPU temperature",
      "Memory usage"
    ],
    "note": "S.M.A.R.T. predicts disk failure."
  },
  {
    "category": "storage",
    "question": "Which storage technology has no moving parts?",
    "answer": "SSD",
    "options": [
      "HDD",
      "SSD",
      "Blu-ray",
      "Tape"
    ],
    "note": "SSDs use flash memory."
  },
  {
    "category": "email",
    "question": "Which protocol retrieves email and typically removes it from the server?",
    "answer": "POP3",
    "options": [
      "POP3",
      "IMAP",
      "SMTP",
      "LDAP"
    ],
    "note": "POP3 traditionally downloads mail locally."
  },
  {
    "category": "email",
    "question": "What does SPF help prevent?",
    "answer": "Email spoofing",
    "options": [
      "Email spoofing",
      "Malware",
      "Encryption failures",
      "DNS poisoning"
    ],
    "note": "SPF validates sending hosts."
  },
  {
    "category": "email",
    "question": "What does DKIM provide?",
    "answer": "Message signing",
    "options": [
      "Message signing",
      "Encryption",
      "Compression",
      "Spam filtering"
    ],
    "note": "DKIM digitally signs email."
  },
  {
    "category": "email",
    "question": "What does DMARC do?",
    "answer": "Provides policy for SPF and DKIM failures",
    "options": [
      "Provides policy for SPF and DKIM failures",
      "Encrypts email",
      "Routes mail",
      "Creates MX records"
    ],
    "note": "DMARC tells receivers what action to take."
  },
  {
    "category": "dns",
    "question": "Which DNS record identifies authoritative name servers?",
    "answer": "NS",
    "options": [
      "NS",
      "MX",
      "PTR",
      "TXT"
    ],
    "note": "NS records point to authoritative DNS servers."
  },
  {
    "category": "dns",
    "question": "Which DNS record is commonly used for autodiscover and SIP services?",
    "answer": "SRV",
    "options": [
      "SRV",
      "PTR",
      "TXT",
      "AAAA"
    ],
    "note": "SRV records locate services."
  },
  {
    "category": "dns",
    "question": "Which DNS record is commonly used for SPF, DKIM, and verification data?",
    "answer": "TXT",
    "options": [
      "TXT",
      "MX",
      "A",
      "PTR"
    ],
    "note": "TXT stores miscellaneous text data."
  },
  {
    "category": "printers",
    "question": "What printer component melts toner onto paper?",
    "answer": "Fuser",
    "options": [
      "Fuser",
      "Transfer roller",
      "Pickup roller",
      "Corona wire"
    ],
    "note": "The fuser uses heat and pressure."
  },
  {
    "category": "printers",
    "question": "Which printer component applies a charge to the drum?",
    "answer": "Corona wire",
    "options": [
      "Corona wire",
      "Fuser",
      "Pickup roller",
      "Transfer belt"
    ],
    "note": "Older laser printers use a corona wire."
  },
  {
    "category": "printers",
    "question": "Which printer type uses an impact print head and ribbon?",
    "answer": "Dot matrix",
    "options": [
      "Laser",
      "Inkjet",
      "Thermal",
      "Dot matrix"
    ],
    "note": "Dot matrix is an impact printer."
  },
  {
    "category": "ports",
    "question": "Which port does IMAP use?",
    "answer": "143",
    "options": [
      "110",
      "143",
      "993",
      "995"
    ],
    "note": "IMAP uses TCP 143."
  },
  {
    "category": "ports",
    "question": "Which port does POP3 use?",
    "answer": "110",
    "options": [
      "110",
      "143",
      "993",
      "995"
    ],
    "note": "POP3 uses TCP 110."
  },
  {
    "category": "ports",
    "question": "Which port is commonly used by SQL Server?",
    "answer": "1433",
    "options": [
      "3306",
      "1521",
      "1433",
      "5432"
    ],
    "note": "Microsoft SQL Server uses TCP 1433."
  },
  {
    "category": "virtualization",
    "question": "Which virtualization technology is built into modern AMD CPUs?",
    "answer": "AMD-V",
    "options": [
      "VT-x",
      "AMD-V",
      "Hyper-V",
      "SR-IOV"
    ],
    "note": "AMD-V enables hardware virtualization."
  },
  {
    "category": "virtualization",
    "question": "Which virtualization technology is built into modern Intel CPUs?",
    "answer": "VT-x",
    "options": [
      "VT-x",
      "AMD-V",
      "Hyper-V",
      "SR-IOV"
    ],
    "note": "VT-x is Intel's virtualization extension."
  },
  {
    "category": "mobile",
    "question": "What type of mobile authentication uses a fingerprint?",
    "answer": "Biometric",
    "options": [
      "PIN",
      "Password",
      "Biometric",
      "Pattern"
    ],
    "note": "Fingerprints are biometric authentication."
  },
  {
    "category": "mobile",
    "question": "What feature allows a lost phone to be remotely erased?",
    "answer": "Remote wipe",
    "options": [
      "Remote wipe",
      "Tethering",
      "NFC",
      "Airplane mode"
    ],
    "note": "Remote wipe protects lost devices."
  },
  {
    "category": "scenario",
    "question": "A technician needs to connect two buildings that are 2 kilometers apart. Which cable type is the BEST choice?",
    "answer": "Single-mode fiber",
    "options": [
      "Cat6",
      "Cat6a",
      "Single-mode fiber",
      "Coaxial"
    ],
    "note": "Single-mode fiber is designed for long-distance communication."
  },
  {
    "category": "scenario",
    "question": "A user needs access to email from multiple devices while keeping messages synchronized. Which protocol should be used?",
    "answer": "IMAP",
    "options": [
      "POP3",
      "SMTP",
      "IMAP",
      "LDAP"
    ],
    "note": "IMAP keeps email synchronized across devices."
  },
  {
    "category": "scenario",
    "question": "A company wants Microsoft 365 email and applications without managing servers. Which cloud model best fits?",
    "answer": "SaaS",
    "options": [
      "IaaS",
      "PaaS",
      "SaaS",
      "Hybrid cloud"
    ],
    "note": "Microsoft 365 is Software as a Service."
  },
  {
    "category": "scenario",
    "question": "A technician installs a wireless network and notices interference from neighboring networks. Which channels should be selected on 2.4 GHz?",
    "answer": "1, 6, and 11",
    "options": [
      "1, 6, and 11",
      "2, 7, and 12",
      "3, 8, and 13",
      "1, 5, and 9"
    ],
    "note": "1, 6, and 11 are the non-overlapping channels."
  },
  {
    "category": "scenario",
    "question": "A user reports slow wireless speeds but excellent signal strength. The AP is using 2.4 GHz in a crowded apartment complex. What is the BEST recommendation?",
    "answer": "Move clients to 5 GHz",
    "options": [
      "Replace the NIC",
      "Move clients to 5 GHz",
      "Change to Cat5",
      "Disable encryption"
    ],
    "note": "5 GHz usually experiences less interference."
  },
  {
    "category": "scenario",
    "question": "A technician must power a wireless access point through the network cable. Which technology should be used?",
    "answer": "PoE",
    "options": [
      "VPN",
      "PoE",
      "NAT",
      "DNS"
    ],
    "note": "Power over Ethernet delivers power and data."
  },
  {
    "category": "scenario",
    "question": "A company wants fault tolerance for two hard drives with an exact copy of data on both drives. Which RAID level should be used?",
    "answer": "RAID 1",
    "options": [
      "RAID 0",
      "RAID 1",
      "RAID 5",
      "RAID 10"
    ],
    "note": "RAID 1 mirrors data."
  },
  {
    "category": "scenario",
    "question": "A technician needs the highest disk performance and does not care about redundancy. Which RAID level should be selected?",
    "answer": "RAID 0",
    "options": [
      "RAID 0",
      "RAID 1",
      "RAID 5",
      "RAID 10"
    ],
    "note": "RAID 0 provides striping without redundancy."
  },
  {
    "category": "scenario",
    "question": "A user can browse websites using IP addresses but cannot access websites using names. What is the MOST likely issue?",
    "answer": "DNS problem",
    "options": [
      "DHCP problem",
      "DNS problem",
      "SMTP problem",
      "PoE problem"
    ],
    "note": "Name resolution failures point to DNS."
  },
  {
    "category": "scenario",
    "question": "A company wants to deploy virtual machines directly on physical hardware without a host operating system. Which hypervisor type should be used?",
    "answer": "Type 1",
    "options": [
      "Type 1",
      "Type 2",
      "Container",
      "Emulator"
    ],
    "note": "Type 1 hypervisors run directly on hardware."
  },
  {
    "category": "scenario",
    "question": "A technician is configuring a smartphone for contactless payments. Which technology must be enabled?",
    "answer": "NFC",
    "options": [
      "GPS",
      "Bluetooth",
      "NFC",
      "LTE"
    ],
    "note": "NFC enables tap-to-pay functionality."
  },
  {
    "category": "scenario",
    "question": "A user reports that all printed pages have unfused toner that wipes off easily. Which printer component is most likely failing?",
    "answer": "Fuser",
    "options": [
      "Fuser",
      "Pickup roller",
      "Transfer roller",
      "Drum"
    ],
    "note": "The fuser melts toner onto paper."
  },
  {
    "category": "scenario",
    "question": "A technician needs a 10 Gbps copper Ethernet connection over a full 100-meter run. Which cable should be installed?",
    "answer": "Cat6a",
    "options": [
      "Cat5e",
      "Cat6",
      "Cat6a",
      "Cat3"
    ],
    "note": "Cat6a is the standard answer for 10GBASE-T at 100 meters."
  },
  {
    "category": "scenario",
    "question": "A user can receive email but cannot send email. Which protocol should be investigated first?",
    "answer": "SMTP",
    "options": [
      "SMTP",
      "POP3",
      "IMAP",
      "LDAP"
    ],
    "note": "SMTP handles outbound mail."
  },
  {
    "category": "scenario",
    "question": "A company wants cloud-hosted virtual servers while retaining responsibility for the operating system and applications. Which cloud model is being used?",
    "answer": "IaaS",
    "options": [
      "IaaS",
      "PaaS",
      "SaaS",
      "DaaS"
    ],
    "note": "IaaS provides infrastructure only."
  }
]